SDKFeishu/SDKFeishu.py
SDKFeishu/__init__.py
sdkfeishu-0.0.1.dist-info/METADATA
sdkfeishu-0.0.1.dist-info/WHEEL
sdkfeishu-0.0.1.dist-info/top_level.txt
sdkfeishu-0.0.1.dist-info/RECORD
