Metadata-Version: 2.4
Name: SDKFeishu
Version: 0.0.1
Summary: Third-party Python SDK for Feishu Open Platform API
Home-page: https://github.com/SRInternet/SDKFeishu
Author: SRInternet
Author-email: srinternet@qq.com
Classifier: Programming Language :: Python :: 3
Classifier: License :: OSI Approved :: MIT License
Classifier: Operating System :: OS Independent
Requires-Python: >=3.6
Requires-Dist: requests>=2.25.1
Requires-Dist: requests-toolbelt>=0.9.1
Dynamic: author
Dynamic: author-email
Dynamic: classifier
Dynamic: description
Dynamic: description-content-type
Dynamic: home-page
Dynamic: requires-dist
Dynamic: requires-python
Dynamic: summary
